RhythmCount/__init__.py
RhythmCount/data_processing.py
RhythmCount/helpers.py
RhythmCount/plot.py
RhythmCount-1.1.dist-info/LICENSE.txt
RhythmCount-1.1.dist-info/METADATA
RhythmCount-1.1.dist-info/WHEEL
RhythmCount-1.1.dist-info/top_level.txt
RhythmCount-1.1.dist-info/RECORD
