Metadata-Version: 2.1
Name: RhythmCount
Version: 1.1
Summary: Python package to analyse the rhythmicity in count data
Home-page: https://github.com/ninavelikajne/RhythmCount
Author: Nina Velikajne, Miha Moškon
Author-email: nv6920@student.uni-lj.si, miha.moskon@fri.uni-lj.si
License: UNKNOWN
Keywords: cosinor,rhytmometry,regression,count data
Platform: UNKNOWN
Classifier: Programming Language :: Python :: 3
Classifier: License :: OSI Approved :: MIT License
Classifier: Operating System :: OS Independent
Requires-Python: >=3.6
License-File: LICENSE.txt
Requires-Dist: pandas
Requires-Dist: numpy
Requires-Dist: matplotlib
Requires-Dist: statsmodels
Requires-Dist: scipy
